aichopen_tools/json_loader.py
aichopen_tools/logger.py
aichopen_tools-0.0.2.dist-info/METADATA
aichopen_tools-0.0.2.dist-info/WHEEL
aichopen_tools-0.0.2.dist-info/top_level.txt
aichopen_tools-0.0.2.dist-info/RECORD
