Metadata-Version: 2.1
Name: aichopen-tools
Version: 0.0.2
Summary: Package to aggregate tools used and developed by the ai-team
Home-page: https://github.com/echOpen/aichopen-tools.git
Author: Joep Barmentlo & Alexandre Carlot
Author-email: joep.barmentlo@echopenfactory.com, alexandre.carlot@echopenfactory.com
Project-URL: Bug Tracker, https://github.com/echOpen/aichopen-tools/issues
Classifier: Programming Language :: Python :: 3
Classifier: Operating System :: OS Independent
Requires-Python: ~=3.8
